yaml2tree/__init__.py
yaml2tree/usage.md
yaml2tree/yaml2tree.py
yaml2tree-0.3.dist-info/LICENSE
yaml2tree-0.3.dist-info/METADATA
yaml2tree-0.3.dist-info/WHEEL
yaml2tree-0.3.dist-info/entry_points.txt
yaml2tree-0.3.dist-info/top_level.txt
yaml2tree-0.3.dist-info/RECORD
