Metadata-Version: 2.1
Name: yaml2tree
Version: 0.3
Summary: Creates a tree of directories, specified using nested lists in YAML
Home-page: https://github.com/0cd/yaml2tree
Author: Puneet Arora
License: UNKNOWN
Platform: UNKNOWN
Classifier: Development Status :: 3 - Alpha
Classifier: License :: OSI Approved :: MIT License
Classifier: Programming Language :: Python :: 3
Requires-Python: >=3
Requires-Dist: pyyaml
